{
  "item_blink": {
    "AbilityCooldown": 15.0,
    "AbilityManaCost": 0,
    "ItemCost": 2250
  },
  "item_overwhelming_blink": {
    "AbilityCooldown": 15.0,
    "AbilityManaCost": 0,
    "ItemCost": 6800
  },
  "item_swift_blink": {
    "AbilityCooldown": 15.0,
    "AbilityManaCost": 0,
    "ItemCost": 6800
  },
  "item_arcane_blink": {
    "AbilityCooldown": 7.0,
    "AbilityManaCost": 0,
    "ItemCost": 6800,
    "bonus_intellect": 25,
    "mana_amount": 100
  },
  "item_recipe_arcane_blink": {
    "ItemCost": 1750,
    "ItemRecipe": 1,
    "ItemResult": "item_arcane_blink",
    "ItemRequirements": {
      "01": "item_blink*;item_mystic_staff"
    }
  },
  "item_recipe_swift_blink": {
    "ItemCost": 1750,
    "ItemRecipe": 1,
    "ItemResult": "item_swift_blink",
    "ItemRequirements": {
      "01": "item_blink*;item_eagle"
    }
  },
  "item_recipe_overwhelming_blink": {
    "ItemCost": 1750,
    "ItemRecipe": 1,
    "ItemResult": "item_overwhelming_blink",
    "ItemRequirements": {
      "01": "item_blink*;item_reaver"
    }
  },
  "item_blades_of_attack": {
    "ItemCost": 450
  },
  "item_broadsword": {
    "ItemCost": 1000
  },
  "item_chainmail": {
    "ItemCost": 550
  },
  "item_claymore": {
    "ItemCost": 1350
  },
  "item_helm_of_iron_will": {
    "ItemCost": 975
  },
  "item_javelin": {
    "ItemCost": 900
  },
  "item_mithril_hammer": {
    "ItemCost": 1600
  },
  "item_platemail": {
    "ItemCost": 1400
  },
  "item_quarterstaff": {
    "ItemCost": 875
  },
  "item_quelling_blade": {
    "AbilityCooldown": 4.0,
    "AbilityManaCost": 0,
    "ItemCost": 100
  },
  "item_faerie_fire": {
    "AbilityCooldown": 5.0,
    "ItemCost": 65
  },
  "item_infused_raindrop": {
    "AbilityCooldown": 7.0,
    "ItemCost": 225,
    "mana_regen": 0.8
  },
  "item_wind_lace": {
    "ItemCost": 250
  },
  "item_ring_of_protection": {
    "ItemCost": 175
  },
  "item_stout_shield": {
    "ItemCost": 100
  },
  "item_recipe_moon_shard": {
    "ItemCost": 0,
    "ItemRecipe": 1,
    "ItemResult": "item_moon_shard",
    "ItemRequirements": {
      "01": "item_hyperstone;item_hyperstone"
    }
  },
  "item_moon_shard": {
    "ItemCost": 4000
  },
  "item_gauntlets": {
    "ItemCost": 140
  },
  "item_slippers": {
    "ItemCost": 140
  },
  "item_mantle": {
    "ItemCost": 140,
    "bonus_intellect": 3
  },
  "item_branches": {
    "AbilityCooldown": 0.0,
    "ItemCost": 50,
    "bonus_all_stats": 1
  },
  "item_belt_of_strength": {
    "ItemCost": 450
  },
  "item_boots_of_elves": {
    "ItemCost": 450
  },
  "item_robe": {
    "ItemCost": 450,
    "bonus_intellect": 6
  },
  "item_circlet": {
    "ItemCost": 155,
    "bonus_all_stats": 2
  },
  "item_crown": {
    "ItemCost": 450,
    "bonus_all_stats": 4
  },
  "item_diadem": {
    "ItemCost": 1000,
    "bonus_all_stats": 6
  },
  "item_ogre_axe": {
    "ItemCost": 1000
  },
  "item_blade_of_alacrity": {
    "ItemCost": 1000
  },
  "item_staff_of_wizardry": {
    "ItemCost": 1000,
    "bonus_intellect": 10
  },
  "item_ultimate_orb": {
    "ItemCost": 2800,
    "bonus_all_stats": 15
  },
  "item_gloves": {
    "ItemCost": 450
  },
  "item_blitz_knuckles": {
    "ItemCost": 1000
  },
  "item_lifesteal": {
    "ItemCost": 900
  },
  "item_voodoo_mask": {
    "ItemCost": 700
  },
  "item_ring_of_regen": {
    "ItemCost": 175
  },
  "item_sobi_mask": {
    "ItemCost": 175,
    "bonus_mana_regen": 0.7
  },
  "item_boots": {
    "ItemCost": 500
  },
  "item_gem": {
    "AbilityCooldown": 12,
    "ItemCost": 900
  },
  "item_cloak": {
    "ItemCost": 800
  },
  "item_talisman_of_evasion": {
    "ItemCost": 1300
  },
  "item_cheese": {
    "AbilityCooldown": 40.0,
    "ItemCost": 1000,
    "mana_restore": 1500
  },
  "item_magic_stick": {
    "AbilityCooldown": 17.0,
    "ItemCost": 200
  },
  "item_recipe_magic_wand": {
    "ItemCost": 150,
    "ItemRecipe": 1,
    "ItemResult": "item_magic_wand",
    "ItemRequirements": {
      "01": "item_magic_stick*;item_branches;item_branches"
    }
  },
  "item_magic_wand": {
    "AbilityCooldown": 15.0,
    "ItemCost": 450,
    "bonus_all_stats": 3
  },
  "item_ghost": {
    "AbilityCooldown": 22.0,
    "ItemCost": 1500,
    "bonus_all_stats": 5
  },
  "item_clarity": {
    "ItemCost": 50,
    "mana_regen": 6
  },
  "item_enchanted_mango": {
    "ItemCost": 65,
    "replenish_amount": 100
  },
  "item_famango": {
    "AbilityCooldown": 5,
    "ItemCost": 0,
    "replenish_amount": 125
  },
  "item_great_famango": {
    "AbilityCooldown": 5,
    "ItemCost": 0,
    "replenish_amount": 400
  },
  "item_greater_famango": {
    "AbilityCooldown": 5,
    "ItemCost": 0,
    "replenish_amount": 900
  },
  "item_recipe_great_famango": {
    "ItemCost": 0,
    "ItemRecipe": 1,
    "ItemResult": "item_great_famango",
    "ItemRequirements": {
      "01": "item_famango;item_famango;item_famango"
    }
  },
  "item_recipe_greater_famango": {
    "ItemCost": 0,
    "ItemRecipe": 1,
    "ItemResult": "item_greater_famango",
    "ItemRequirements": {
      "01": "item_great_famango;item_great_famango"
    }
  },
  "item_blood_grenade": {
    "AbilityCooldown": 10,
    "ItemCost": 50
  },
  "item_royale_with_cheese": {
    "AbilityCooldown": 40.0,
    "ItemCost": 2
  },
  "item_flask": {
    "ItemCost": 100
  },
  "item_dust": {
    "AbilityCooldown": 30.0,
    "AbilityManaCost": 0,
    "ItemCost": 80
  },
  "item_bottle": {
    "AbilityCooldown": 0.5,
    "ItemCost": 675,
    "mana_restore": 60
  },
  "item_ward_observer": {
    "AbilityCooldown": 1.0,
    "ItemCost": 0
  },
  "item_ward_sentry": {
    "AbilityCooldown": 1.0,
    "ItemCost": 50
  },
  "item_recipe_ward_dispenser": {
    "ItemCost": 0,
    "ItemRecipe": 1,
    "ItemResult": "item_ward_dispenser",
    "ItemRequirements": {
      "01": "item_ward_sentry;item_ward_observer",
      "02": "item_ward_sentry;item_ward_dispenser",
      "03": "item_ward_dispenser*;item_ward_observer",
      "04": "item_ward_dispenser*;item_ward_dispenser"
    }
  },
  "item_ward_dispenser": {
    "ItemCost": 50,
    "AbilityCooldown": 0
  },
  "item_tango": {
    "ItemCost": 90
  },
  "item_tango_single": {
    "ItemCost": 30
  },
  "item_courier": {
    "ItemCost": 50
  },
  "item_flying_courier": {
    "ItemCost": 100
  },
  "item_tpscroll": {
    "AbilityCooldown": 80.0,
    "AbilityManaCost": 75,
    "ItemCost": 100
  },
  "item_recipe_travel_boots": {
    "ItemCost": 2000,
    "ItemRecipe": 1,
    "ItemResult": "item_travel_boots",
    "ItemRequirements": {
      "01": "item_boots*"
    }
  },
  "item_recipe_travel_boots_2": {
    "ItemCost": 0,
    "ItemRecipe": 1,
    "ItemResult": "item_travel_boots_2",
    "ItemRequirements": {
      "01": "item_travel_boots*;item_recipe_travel_boots"
    }
  },
  "item_travel_boots": {
    "ItemCost": 2500
  },
  "item_travel_boots_2": {
    "ItemCost": 4500
  },
  "item_recipe_phase_boots": {
    "ItemCost": 0,
    "ItemRecipe": 1,
    "ItemResult": "item_phase_boots",
    "ItemRequirements": {
      "01": "item_boots*;item_chainmail;item_blades_of_attack"
    }
  },
  "item_phase_boots": {
    "AbilityCooldown": 8.0,
    "ItemCost": 1500
  },
  "item_demon_edge": {
    "ItemCost": 2200
  },
  "item_eagle": {
    "ItemCost": 2800
  },
  "item_reaver": {
    "ItemCost": 2800
  },
  "item_relic": {
    "ItemCost": 3400
  },
  "item_hyperstone": {
    "ItemCost": 2000
  },
  "item_ring_of_health": {
    "ItemCost": 700
  },
  "item_ring_of_tarrasque": {
    "ItemCost": 1800
  },
  "item_void_stone": {
    "ItemCost": 700,
    "bonus_mana_regen": 1.75
  },
  "item_tiara_of_selemene": {
    "ItemCost": 1800,
    "bonus_mana_regen": 6
  },
  "item_mystic_staff": {
    "ItemCost": 2800,
    "bonus_intellect": 25
  },
  "item_energy_booster": {
    "ItemCost": 800,
    "bonus_mana": 250
  },
  "item_point_booster": {
    "ItemCost": 1200,
    "bonus_mana": 175
  },
  "item_vitality_booster": {
    "ItemCost": 1000
  },
  "item_fluffy_hat": {
    "ItemCost": 250
  },
  "item_recipe_power_treads": {
    "ItemCost": 0,
    "ItemRecipe": 1,
    "ItemResult": "item_power_treads",
    "ItemRequirements": {
      "01": "item_boots*;item_gloves;item_belt_of_strength",
      "04": "item_boots*;item_gloves;item_robe",
      "06": "item_boots*;item_gloves;item_boots_of_elves"
    }
  },
  "item_power_treads": {
    "ItemCost": 1400
  },
  "item_recipe_samurai_tabi": {
    "ItemCost": 1100,
    "ItemRecipe": 1,
    "ItemResult": "item_samurai_tabi",
    "ItemRequirements": {
      "01": "item_belt_of_strength;item_boots_of_elves;item_robe;item_ultimate_orb"
    }
  },
  "item_samurai_tabi": {
    "ItemCost": 5250,
    "bonus_all_stats": 10
  },
  "item_recipe_hermes_sandals": {
    "ItemCost": 500,
    "ItemRecipe": 1,
    "ItemResult": "item_hermes_sandals",
    "ItemRequirements": {
      "01": "item_phase_boots;item_eagle"
    }
  },
  "item_hermes_sandals": {
    "AbilityCooldown": 10.0,
    "ItemCost": 4800
  },
  "item_recipe_witches_switch": {
    "ItemCost": 625,
    "ItemRecipe": 1,
    "ItemResult": "item_witches_switch",
    "ItemRequirements": {
      "01": "item_buckler;item_ring_of_basilius;item_headdress"
    }
  },
  "item_witches_switch": {
    "AbilityCooldown": 1.0,
    "ItemCost": 1900,
    "bonus_mana_regen": 2,
    "aura_mana_regen": 1.5
  },
  "item_recipe_grandmasters_glaive": {
    "ItemCost": 0,
    "ItemRecipe": 1,
    "ItemResult": "item_grandmasters_glaive",
    "ItemRequirements": ""
  },
  "item_recipe_lunar_crest": {
    "ItemCost": 250,
    "ItemRecipe": 1,
    "ItemResult": "item_lunar_crest",
    "ItemRequirements": {
      "01": "item_cloak;item_wind_lace;item_vitality_booster"
    }
  },
  "item_lunar_crest": {
    "AbilityCooldown": 30.0,
    "ItemCost": 2300
  },
  "item_recipe_phylactery": {
    "ItemCost": 200,
    "ItemRecipe": 1,
    "ItemResult": "item_phylactery",
    "ItemRequirements": {
      "01": "item_point_booster;item_diadem"
    }
  },
  "item_phylactery": {
    "AbilityCooldown": 6.0,
    "ItemCost": 2400,
    "bonus_mana": 200,
    "bonus_all_stats": 7
  },
  "item_recipe_angels_demise": {
    "ItemCost": 600,
    "ItemRecipe": 1,
    "ItemResult": "item_angels_demise",
    "ItemRequirements": {
      "01": "item_phylactery;item_lesser_crit"
    }
  },
  "item_angels_demise": {
    "AbilityCooldown": 6.0,
    "ItemCost": 5000,
    "bonus_mana": 200,
    "bonus_all_stats": 8
  },
  "item_grandmasters_glaive": {
    "ItemCost": 5000
  },
  "item_recipe_hand_of_midas": {
    "ItemCost": 1750,
    "ItemRecipe": 1,
    "ItemResult": "item_hand_of_midas",
    "ItemRequirements": {
      "01": "item_gloves*"
    }
  },
  "item_hand_of_midas": {
    "AbilityCooldown": 0,
    "AbilityManaCost": 0,
    "ItemCost": 2200
  },
  "item_aetherial_halo": {
    "AbilityCooldown": 24,
    "AbilityManaCost": 100,
    "ItemCost": 5900,
    "bonus_intellect": 40,
    "mana_regen_multiplier": 100
  },
  "item_recipe_oblivion_staff": {
    "ItemCost": 0,
    "ItemRecipe": 1,
    "ItemResult": "item_oblivion_staff",
    "ItemRequirements": {
      "01": "item_blitz_knuckles;item_sobi_mask;item_robe"
    }
  },
  "item_oblivion_staff": {
    "ItemCost": 1625,
    "bonus_intellect": 10,
    "bonus_mana_regen": 1.0
  },
  "item_recipe_witch_blade": {
    "ItemCost": 600,
    "ItemRecipe": 1,
    "ItemResult": "item_witch_blade",
    "ItemRequirements": {
      "01": "item_oblivion_staff;item_chainmail"
    }
  },
  "item_witch_blade": {
    "AbilityCooldown": 9.0,
    "ItemCost": 2775,
    "bonus_intellect": 12,
    "bonus_mana_regen": 1.5
  },
  "item_recipe_pers": {
    "ItemCost": 0,
    "ItemRecipe": 1,
    "ItemResult": "item_pers",
    "ItemRequirements": {
      "01": "item_ring_of_health;item_void_stone"
    }
  },
  "item_pers": {
    "ItemCost": 1400,
    "bonus_mana_regen": 2.25
  },
  "item_cornucopia": {
    "ItemCost": 1200,
    "bonus_mana_regen": 2
  },
  "item_recipe_poor_mans_shield": {
    "ItemCost": 0,
    "ItemRecipe": 1,
    "ItemResult": "item_poor_mans_shield",
    "ItemRequirements": ""
  },
  "item_poor_mans_shield": {
    "ItemCost": 0
  },
  "item_satchel": {
    "ItemCost": 0,
    "bonus_all_stats": 5
  },
  "item_recipe_bracer": {
    "ItemCost": 210,
    "ItemRecipe": 1,
    "ItemResult": "item_bracer",
    "ItemRequirements": {
      "01": "item_circlet;item_gauntlets"
    }
  },
  "item_bracer": {
    "ItemCost": 505,
    "bonus_intellect": "2 4"
  },
  "item_recipe_wraith_band": {
    "ItemCost": 210,
    "ItemRecipe": 1,
    "ItemResult": "item_wraith_band",
    "ItemRequirements": {
      "01": "item_circlet;item_slippers"
    }
  },
  "item_wraith_band": {
    "ItemCost": 505,
    "bonus_intellect": "2 4"
  },
  "item_recipe_null_talisman": {
    "ItemCost": 210,
    "ItemRecipe": 1,
    "ItemResult": "item_null_talisman",
    "ItemRequirements": {
      "01": "item_circlet;item_mantle"
    }
  },
  "item_null_talisman": {
    "ItemCost": 505,
    "bonus_intellect": "5 10",
    "bonus_mana_regen": "1.0 2.0"
  },
  "item_recipe_mekansm": {
    "ItemCost": 800,
    "ItemRecipe": 1,
    "ItemResult": "item_mekansm",
    "ItemRequirements": {
      "01": "item_headdress;item_chainmail"
    }
  },
  "item_mekansm": {
    "AbilityCooldown": 50.0,
    "AbilityManaCost": 100,
    "ItemCost": 1775
  },
  "item_recipe_vladmir": {
    "ItemCost": 0,
    "ItemRecipe": 1,
    "ItemResult": "item_vladmir",
    "ItemRequirements": {
      "01": "item_buckler;item_ring_of_basilius;item_lifesteal;item_blades_of_attack"
    }
  },
  "item_vladmir": {
    "ItemCost": 2200,
    "mana_regen": 0.75
  },
  "item_recipe_wraith_pact": {
    "ItemCost": 400,
    "ItemRecipe": 1,
    "ItemResult": "item_wraith_pact",
    "ItemRequirements": {
      "01": "item_vladmir;item_point_booster"
    }
  },
  "item_wraith_pact": {
    "AbilityCooldown": 60,
    "AbilityDuration": 25,
    "AbilityManaCost": 100,
    "ItemCost": 3800,
    "bonus_mana": 250
  },
  "item_recipe_buckler": {
    "ItemCost": 250,
    "ItemRecipe": 1,
    "ItemResult": "item_buckler",
    "ItemRequirements": {
      "01": "item_ring_of_protection"
    }
  },
  "item_buckler": {
    "ItemCost": 425
  },
  "item_recipe_ring_of_basilius": {
    "ItemCost": 250,
    "ItemRecipe": 1,
    "ItemResult": "item_ring_of_basilius",
    "ItemRequirements": {
      "01": "item_sobi_mask"
    }
  },
  "item_ring_of_basilius": {
    "ItemCost": 425,
    "mana_regen": 0.5,
    "aura_mana_regen": 1.0
  },
  "item_recipe_holy_locket": {
    "ItemCost": 900,
    "ItemRecipe": 1,
    "ItemResult": "item_holy_locket",
    "ItemRequirements": {
      "01": "item_diadem;item_magic_wand"
    }
  },
  "item_holy_locket": {
    "ItemCost": 2350,
    "AbilityCooldown": 0.0,
    "bonus_mana": 0,
    "bonus_all_stats": 9
  },
  "item_recipe_pipe": {
    "ItemCost": 700,
    "ItemRecipe": 1,
    "ItemResult": "item_pipe",
    "ItemRequirements": {
      "01": "item_cloak*;item_headdress;item_ring_of_tarrasque"
    }
  },
  "item_pipe": {
    "AbilityCooldown": 60.0,
    "AbilityManaCost": 150,
    "ItemCost": 3725,
    "bonus_all_stats": 0
  },
  "item_recipe_urn_of_shadows": {
    "ItemCost": 375,
    "ItemRecipe": 1,
    "ItemResult": "item_urn_of_shadows",
    "ItemRequirements": {
      "01": "item_sobi_mask;item_ring_of_protection;item_circlet"
    }
  },
  "item_urn_of_shadows": {
    "AbilityCooldown": 7.0,
    "ItemCost": 880,
    "mana_regen": 1.4,
    "bonus_all_stats": 2
  },
  "item_recipe_headdress": {
    "ItemCost": 250,
    "ItemRecipe": 1,
    "ItemResult": "item_headdress",
    "ItemRequirements": {
      "01": "item_ring_of_regen"
    }
  },
  "item_headdress": {
    "ItemCost": 425
  },
  "item_recipe_sheepstick": {
    "ItemCost": 600,
    "ItemRecipe": 1,
    "ItemResult": "item_sheepstick",
    "ItemRequirements": {
      "01": "item_mystic_staff;item_tiara_of_selemene"
    }
  },
  "item_sheepstick": {
    "AbilityCooldown": 20.0,
    "AbilityManaCost": 250,
    "ItemCost": 5200,
    "bonus_intellect": 30,
    "bonus_mana_regen": 8.5
  },
  "item_caster_rapier": {
    "ItemCost": 5600,
    "AbilityCooldown": 9
  },
  "item_recipe_orchid": {
    "ItemCost": 450,
    "ItemRecipe": 1,
    "ItemResult": "item_orchid",
    "ItemRequirements": {
      "01": "item_oblivion_staff;item_cornucopia"
    }
  },
  "item_orchid": {
    "AbilityCooldown": 18.0,
    "AbilityManaCost": 125,
    "ItemCost": 3275,
    "bonus_mana_regen": 3.25,
    "bonus_intellect": 10
  },
  "item_recipe_bloodthorn": {
    "ItemCost": 450,
    "ItemRecipe": 1,
    "ItemResult": "item_bloodthorn",
    "ItemRequirements": {
      "01": "item_orchid*;item_javelin;item_hyperstone"
    }
  },
  "item_bloodthorn": {
    "AbilityCooldown": 15.0,
    "AbilityManaCost": 125,
    "ItemCost": 6625,
    "bonus_intellect": 10,
    "bonus_mana_regen": 3.5
  },
  "item_recipe_echo_sabre": {
    "ItemCost": 0,
    "ItemRecipe": 1,
    "ItemResult": "item_echo_sabre",
    "ItemRequirements": {
      "01": "item_ogre_axe;item_broadsword;item_void_stone"
    }
  },
  "item_echo_sabre": {
    "AbilityCooldown": 5,
    "AbilityManaCost": 0,
    "ItemCost": 2700,
    "bonus_mana_regen": 1.75
  },
  "item_recipe_cyclone": {
    "ItemCost": 675,
    "ItemRecipe": 1,
    "ItemResult": "item_cyclone",
    "ItemRequirements": {
      "01": "item_staff_of_wizardry;item_void_stone;item_wind_lace"
    }
  },
  "item_cyclone": {
    "AbilityCooldown": 23.0,
    "AbilityManaCost": 175,
    "ItemCost": 2625,
    "bonus_intellect": 10,
    "bonus_mana_regen": 2.5
  },
  "item_recipe_wind_waker": {
    "ItemCost": 1400,
    "ItemRecipe": 1,
    "ItemResult": "item_wind_waker",
    "ItemRequirements": {
      "01": "item_cyclone*;item_mystic_staff"
    }
  },
  "item_wind_waker": {
    "AbilityCooldown": 16.0,
    "AbilityManaCost": 175,
    "ItemCost": 6825,
    "bonus_mana_regen": 3.0,
    "bonus_intellect": 35
  },
  "item_recipe_aether_lens": {
    "ItemCost": 775,
    "ItemRecipe": 1,
    "ItemResult": "item_aether_lens",
    "ItemRequirements": {
      "01": "item_energy_booster;item_void_stone"
    }
  },
  "item_aether_lens": {
    "ItemCost": 2275,
    "bonus_mana": 300,
    "bonus_mana_regen": 2.5
  },
  "item_recipe_force_staff": {
    "ItemCost": 950,
    "ItemRecipe": 1,
    "ItemResult": "item_force_staff",
    "ItemRequirements": {
      "01": "item_staff_of_wizardry;item_fluffy_hat"
    }
  },
  "item_force_staff": {
    "AbilityCooldown": 19.0,
    "AbilityManaCost": 150,
    "ItemCost": 2200,
    "bonus_intellect": 10
  },
  "item_recipe_hurricane_pike": {
    "ItemCost": 350,
    "ItemRecipe": 1,
    "ItemResult": "item_hurricane_pike",
    "ItemRequirements": {
      "01": "item_force_staff*;item_dragon_lance"
    }
  },
  "item_hurricane_pike": {
    "AbilityCooldown": 19.0,
    "AbilityManaCost": 150,
    "ItemCost": 4450,
    "bonus_intellect": 15
  },
  "item_recipe_dagon": {
    "ItemCost": 1150,
    "ItemRecipe": 1,
    "ItemResult": "item_dagon",
    "ItemRequirements": {
      "01": "item_diadem;item_voodoo_mask"
    }
  },
  "item_recipe_dagon_2": {
    "ItemCost": 0,
    "ItemRecipe": 1,
    "ItemResult": "item_dagon_2",
    "ItemRequirements": {
      "02": "item_dagon*;item_recipe_dagon"
    }
  },
  "item_recipe_dagon_3": {
    "ItemCost": 0,
    "ItemRecipe": 1,
    "ItemResult": "item_dagon_3",
    "ItemRequirements": {
      "02": "item_dagon_2*;item_recipe_dagon"
    }
  },
  "item_recipe_dagon_4": {
    "ItemCost": 0,
    "ItemRecipe": 1,
    "ItemResult": "item_dagon_4",
    "ItemRequirements": {
      "02": "item_dagon_3*;item_recipe_dagon"
    }
  },
  "item_recipe_dagon_5": {
    "ItemCost": 0,
    "ItemRecipe": 1,
    "ItemResult": "item_dagon_5",
    "ItemRequirements": {
      "02": "item_dagon_4*;item_recipe_dagon"
    }
  },
  "item_dagon": {
    "AbilityCooldown": "27 24 21 18 15",
    "AbilityManaCost": "120 140 160 180 200",
    "ItemCost": 2850,
    "bonus_int": "7 9 11 13 15"
  },
  "item_dagon_2": {
    "AbilityCooldown": "27 24 21 18 15",
    "AbilityManaCost": "120 140 160 180 200",
    "ItemCost": 4000,
    "bonus_int": "7 9 11 13 15"
  },
  "item_dagon_3": {
    "AbilityCooldown": "27 24 21 18 15",
    "AbilityManaCost": "120 140 160 180 200",
    "ItemCost": 5150,
    "bonus_int": "7 9 11 13 15"
  },
  "item_dagon_4": {
    "AbilityCooldown": "27 24 21 18 15",
    "AbilityManaCost": "120 140 160 180 200",
    "ItemCost": 6300,
    "bonus_int": "7 9 11 13 15"
  },
  "item_dagon_5": {
    "AbilityCooldown": "27 24 21 18 15",
    "AbilityManaCost": "120 140 160 180 200",
    "ItemCost": 7450,
    "bonus_int": "7 9 11 13 15"
  },
  "item_recipe_necronomicon": {
    "ItemCost": 1250,
    "ItemRecipe": 1,
    "ItemResult": "item_necronomicon",
    "ItemRequirements": {
      "01": "item_sobi_mask;item_sobi_mask;item_belt_of_strength"
    }
  },
  "item_recipe_necronomicon_2": {
    "ItemCost": 0,
    "ItemRecipe": 1,
    "ItemResult": "item_necronomicon_2",
    "ItemRequirements": {
      "01": "item_necronomicon*;item_recipe_necronomicon"
    }
  },
  "item_recipe_necronomicon_3": {
    "ItemCost": 0,
    "ItemRecipe": 1,
    "ItemResult": "item_necronomicon_3",
    "ItemRequirements": {
      "01": "item_necronomicon_2*;item_recipe_necronomicon"
    }
  },
  "item_necronomicon": {
    "AbilityCooldown": 80.0,
    "AbilityManaCost": 150,
    "ItemCost": 2050,
    "bonus_mana_regen": "2 3 4"
  },
  "item_necronomicon_2": {
    "AbilityCooldown": 80.0,
    "AbilityManaCost": 150,
    "ItemCost": 3300,
    "bonus_mana_regen": "2 3 4"
  },
  "item_necronomicon_3": {
    "AbilityCooldown": 80.0,
    "AbilityManaCost": 150,
    "ItemCost": 4550,
    "bonus_mana_regen": "2 3 4"
  },
  "item_recipe_ultimate_scepter": {
    "ItemCost": 0,
    "ItemRecipe": 1,
    "ItemResult": "item_ultimate_scepter",
    "ItemRequirements": {
      "01": "item_point_booster;item_staff_of_wizardry;item_ogre_axe;item_blade_of_alacrity"
    }
  },
  "item_ultimate_scepter": {
    "ItemCost": 4200,
    "bonus_all_stats": 10,
    "bonus_mana": 175
  },
  "item_recipe_ultimate_scepter_2": {
    "ItemCost": 1600,
    "ItemRecipe": 1,
    "ItemResult": "item_ultimate_scepter_2",
    "ItemRequirements": {
      "01": "item_ultimate_scepter"
    }
  },
  "item_ultimate_scepter_2": {
    "ItemCost": 5800
  },
  "item_ultimate_scepter_roshan": {
    "ItemCost": 5800
  },
  "item_aghanims_shard": {
    "ItemCost": 1400
  },
  "item_aghanims_shard_roshan": {
    "ItemCost": 1400
  },
  "item_recipe_refresher": {
    "ItemCost": 200,
    "ItemRecipe": 1,
    "ItemResult": "item_refresher",
    "ItemRequirements": {
      "01": "item_cornucopia;item_ring_of_tarrasque;item_tiara_of_selemene"
    }
  },
  "item_refresher": {
    "AbilityCooldown": 180.0,
    "AbilityManaCost": 350,
    "ItemCost": 5000,
    "bonus_mana_regen": 8.0
  },
  "item_recipe_assault": {
    "ItemCost": 1300,
    "ItemRecipe": 1,
    "ItemResult": "item_assault",
    "ItemRequirements": {
      "01": "item_platemail;item_hyperstone;item_buckler"
    }
  },
  "item_assault": {
    "ItemCost": 5125
  },
  "item_recipe_heart": {
    "ItemCost": 600,
    "ItemRecipe": 1,
    "ItemResult": "item_heart",
    "ItemRequirements": {
      "01": "item_ring_of_tarrasque;item_reaver"
    }
  },
  "item_heart": {
    "ItemCost": 5200
  },
  "item_recipe_black_king_bar": {
    "ItemCost": 1450,
    "ItemRecipe": 1,
    "ItemResult": "item_black_king_bar",
    "ItemRequirements": {
      "01": "item_ogre_axe;item_mithril_hammer"
    }
  },
  "item_black_king_bar": {
    "AbilityCooldown": 95,
    "AbilityManaCost": 50,
    "ItemCost": 4050
  },
  "item_aegis": {
    "ItemCost": 0
  },
  "item_recipe_shivas_guard": {
    "ItemCost": 2050,
    "ItemRecipe": 1,
    "ItemResult": "item_shivas_guard",
    "ItemRequirements": {
      "01": "item_veil_of_discord;item_platemail"
    }
  },
  "item_shivas_guard": {
    "AbilityCooldown": 27,
    "AbilityManaCost": 75,
    "ItemCost": 5175,
    "bonus_intellect": 5
  },
  "item_recipe_bloodstone": {
    "ItemCost": 0,
    "ItemRecipe": 1,
    "ItemResult": "item_bloodstone",
    "ItemRequirements": {
      "01": "item_voodoo_mask;item_soul_booster;item_void_stone"
    }
  },
  "item_bloodstone": {
    "AbilityCooldown": 35.0,
    "AbilityManaCost": 0,
    "ItemCost": 4400,
    "bonus_mana": 500,
    "bonus_mp_regen": 3
  },
  "item_recipe_sphere": {
    "ItemCost": 600,
    "ItemRecipe": 1,
    "ItemResult": "item_sphere",
    "ItemRequirements": {
      "01": "item_ultimate_orb;item_pers"
    }
  },
  "item_sphere": {
    "AbilityCooldown": 14.0,
    "ItemCost": 4800,
    "bonus_all_stats": 16,
    "bonus_mana_regen": 4.25
  },
  "item_recipe_lotus_orb": {
    "ItemCost": 250,
    "ItemRecipe": 1,
    "ItemResult": "item_lotus_orb",
    "ItemRequirements": {
      "01": "item_pers;item_platemail;item_energy_booster"
    }
  },
  "item_lotus_orb": {
    "AbilityCooldown": 15.0,
    "AbilityManaCost": 175,
    "ItemCost": 3850,
    "bonus_mana_regen": 4.0,
    "bonus_mana": 250
  },
  "item_recipe_meteor_hammer": {
    "ItemCost": 300,
    "ItemRecipe": 1,
    "ItemResult": "item_meteor_hammer",
    "ItemRequirements": {
      "01": "item_crown;item_kaya"
    }
  },
  "item_meteor_hammer": {
    "AbilityCooldown": 24,
    "AbilityManaCost": 100,
    "ItemCost": 2850,
    "bonus_intellect": 24,
    "mana_regen_multiplier": 75
  },
  "item_recipe_nullifier": {
    "ItemCost": 0,
    "ItemRecipe": 1,
    "ItemResult": "item_nullifier",
    "ItemRequirements": {
      "01": "item_relic;item_helm_of_iron_will"
    }
  },
  "item_nullifier": {
    "AbilityCooldown": 10.0,
    "AbilityManaCost": 0,
    "ItemCost": 4375
  },
  "item_recipe_aeon_disk": {
    "ItemCost": 1200,
    "ItemRecipe": 1,
    "ItemResult": "item_aeon_disk",
    "ItemRequirements": {
      "01": "item_vitality_booster;item_energy_booster"
    }
  },
  "item_aeon_disk": {
    "AbilityCooldown": "105.0 125.0 145.0 165.0",
    "ItemCost": 3000,
    "bonus_mana": 300
  },
  "item_recipe_kaya": {
    "ItemCost": 650,
    "ItemRecipe": 1,
    "ItemResult": "item_kaya",
    "ItemRequirements": {
      "01": "item_staff_of_wizardry;item_robe"
    }
  },
  "item_kaya": {
    "ItemCost": 2100,
    "bonus_intellect": 16,
    "mana_regen_multiplier": 50
  },
  "item_trident": {
    "ItemCost": 6301,
    "bonus_intellect": 30,
    "mana_regen_multiplier": 30
  },
  "item_refresher_shard": {
    "AbilityCooldown": 180.0,
    "AbilityManaCost": 200,
    "ItemCost": 1000,
    "bonus_mana_regen": 6.0
  },
  "item_recipe_spirit_vessel": {
    "ItemCost": 1200,
    "ItemRecipe": 1,
    "ItemResult": "item_spirit_vessel",
    "ItemRequirements": {
      "01": "item_urn_of_shadows*;item_crown;item_fluffy_hat"
    }
  },
  "item_spirit_vessel": {
    "AbilityCooldown": 7.0,
    "ItemCost": 2780,
    "bonus_mana_regen": 1.75,
    "bonus_all_stats": 6
  },
  "item_recipe_vanguard": {
    "ItemCost": 0,
    "ItemRecipe": 1,
    "ItemResult": "item_vanguard",
    "ItemRequirements": {
      "01": "item_ring_of_health;item_vitality_booster"
    }
  },
  "item_vanguard": {
    "ItemCost": 1700
  },
  "item_recipe_crimson_guard": {
    "ItemCost": 1050,
    "ItemRecipe": 1,
    "ItemResult": "item_crimson_guard",
    "ItemRequirements": {
      "01": "item_vanguard;item_helm_of_iron_will"
    }
  },
  "item_crimson_guard": {
    "AbilityCooldown": 35.0,
    "AbilityManaCost": 75,
    "ItemCost": 3725
  },
  "item_recipe_blade_mail": {
    "ItemCost": 550,
    "ItemRecipe": 1,
    "ItemResult": "item_blade_mail",
    "ItemRequirements": {
      "01": "item_broadsword;item_chainmail"
    }
  },
  "item_blade_mail": {
    "AbilityCooldown": 25.0,
    "AbilityManaCost": 25,
    "ItemCost": 2100,
    "bonus_intellect": 0
  },
  "item_recipe_soul_booster": {
    "ItemCost": 0,
    "ItemRecipe": 1,
    "ItemResult": "item_soul_booster",
    "ItemRequirements": {
      "01": "item_vitality_booster;item_energy_booster;item_point_booster"
    }
  },
  "item_soul_booster": {
    "ItemCost": 3000,
    "bonus_mana": 425
  },
  "item_recipe_hood_of_defiance": {
    "ItemCost": 0,
    "ItemRecipe": 1,
    "ItemResult": "item_hood_of_defiance",
    "ItemRequirements": ""
  },
  "item_hood_of_defiance": {
    "AbilityCooldown": 60.0,
    "AbilityManaCost": 50,
    "ItemCost": 0
  },
  "item_recipe_eternal_shroud": {
    "ItemCost": 900,
    "ItemRecipe": 1,
    "ItemResult": "item_eternal_shroud",
    "ItemRequirements": {
      "01": "item_cloak;item_ogre_axe;item_vitality_booster"
    }
  },
  "item_eternal_shroud": {
    "ItemCost": 3700
  },
  "item_recipe_rapier": {
    "ItemCost": 0,
    "ItemRecipe": 1,
    "ItemResult": "item_rapier",
    "ItemRequirements": {
      "01": "item_relic;item_demon_edge"
    }
  },
  "item_rapier": {
    "ItemCost": 5600,
    "AbilityCooldown": 6
  },
  "item_recipe_monkey_king_bar": {
    "ItemCost": 600,
    "ItemRecipe": 1,
    "ItemResult": "item_monkey_king_bar",
    "ItemRequirements": {
      "01": "item_demon_edge;item_javelin;item_blitz_knuckles"
    }
  },
  "item_monkey_king_bar": {
    "ItemCost": 4700
  },
  "item_recipe_radiance": {
    "ItemCost": 0,
    "ItemRecipe": 1,
    "ItemResult": "item_radiance",
    "ItemRequirements": {
      "01": "item_relic;item_talisman_of_evasion"
    }
  },
  "item_radiance": {
    "ItemCost": 4700
  },
  "item_recipe_butterfly": {
    "ItemCost": 0,
    "ItemRecipe": 1,
    "ItemResult": "item_butterfly",
    "ItemRequirements": {
      "01": "item_eagle;item_talisman_of_evasion;item_claymore"
    }
  },
  "item_butterfly": {
    "ItemCost": 5450
  },
  "item_recipe_greater_crit": {
    "ItemCost": 900,
    "ItemRecipe": 1,
    "ItemResult": "item_greater_crit",
    "ItemRequirements": {
      "01": "item_lesser_crit;item_demon_edge"
    }
  },
  "item_greater_crit": {
    "ItemCost": 5100
  },
  "item_recipe_basher": {
    "ItemCost": 825,
    "ItemRecipe": 1,
    "ItemResult": "item_basher",
    "ItemRequirements": {
      "01": "item_mithril_hammer;item_belt_of_strength"
    }
  },
  "item_basher": {
    "AbilityCooldown": 2.3,
    "ItemCost": 2875
  },
  "item_recipe_bfury": {
    "ItemCost": 450,
    "ItemRecipe": 1,
    "ItemResult": "item_bfury",
    "ItemRequirements": {
      "01": "item_broadsword;item_claymore;item_cornucopia;item_quelling_blade"
    }
  },
  "item_bfury": {
    "AbilityCooldown": 4.0,
    "ItemCost": 4100,
    "bonus_mana_regen": 2.75
  },
  "item_recipe_manta": {
    "ItemCost": 1550,
    "ItemRecipe": 1,
    "ItemResult": "item_manta",
    "ItemRequirements": {
      "01": "item_yasha;item_diadem"
    }
  },
  "item_manta": {
    "AbilityCooldown": 34.0,
    "AbilityManaCost": 125,
    "ItemCost": 4650,
    "bonus_intellect": 10
  },
  "item_recipe_lesser_crit": {
    "ItemCost": 200,
    "ItemRecipe": 1,
    "ItemResult": "item_lesser_crit",
    "ItemRequirements": {
      "01": "item_claymore;item_blades_of_attack"
    }
  },
  "item_lesser_crit": {
    "ItemCost": 2000
  },
  "item_recipe_dragon_lance": {
    "ItemCost": 450,
    "ItemRecipe": 1,
    "ItemResult": "item_dragon_lance",
    "ItemRequirements": {
      "01": "item_blade_of_alacrity;item_belt_of_strength"
    }
  },
  "item_dragon_lance": {
    "ItemCost": 1900
  },
  "item_recipe_armlet": {
    "ItemCost": 625,
    "ItemRecipe": 1,
    "ItemResult": "item_armlet",
    "ItemRequirements": {
      "01": "item_helm_of_iron_will;item_gloves;item_blades_of_attack"
    }
  },
  "item_armlet": {
    "AbilityCooldown": 0.0,
    "ItemCost": 2500
  },
  "item_recipe_invis_sword": {
    "ItemCost": 0,
    "ItemRecipe": 1,
    "ItemResult": "item_invis_sword",
    "ItemRequirements": {
      "01": "item_shadow_amulet*;item_blitz_knuckles;item_broadsword"
    }
  },
  "item_invis_sword": {
    "AbilityCooldown": 25.0,
    "AbilityManaCost": 75,
    "ItemCost": 3000
  },
  "item_recipe_silver_edge": {
    "ItemCost": 250,
    "ItemRecipe": 1,
    "ItemResult": "item_silver_edge",
    "ItemRequirements": {
      "01": "item_invis_sword*;item_demon_edge"
    }
  },
  "item_silver_edge": {
    "AbilityCooldown": 20.0,
    "AbilityManaCost": 75,
    "ItemCost": 5450,
    "bonus_intellect": 0,
    "bonus_mana_regen": 0
  },
  "item_recipe_sange_and_yasha": {
    "ItemCost": 0,
    "ItemRecipe": 1,
    "ItemResult": "item_sange_and_yasha",
    "ItemRequirements": {
      "01": "item_yasha;item_sange"
    }
  },
  "item_sange_and_yasha": {
    "ItemCost": 4200
  },
  "item_recipe_kaya_and_sange": {
    "ItemCost": 0,
    "ItemRecipe": 1,
    "ItemResult": "item_kaya_and_sange",
    "ItemRequirements": {
      "01": "item_sange;item_kaya"
    }
  },
  "item_kaya_and_sange": {
    "ItemCost": 4200,
    "bonus_intellect": 16,
    "mana_regen_multiplier": 50
  },
  "item_recipe_yasha_and_kaya": {
    "ItemCost": 0,
    "ItemRecipe": 1,
    "ItemResult": "item_yasha_and_kaya",
    "ItemRequirements": {
      "01": "item_kaya;item_yasha"
    }
  },
  "item_yasha_and_kaya": {
    "ItemCost": 4200,
    "bonus_intellect": 16,
    "mana_regen_multiplier": 50
  },
  "item_recipe_satanic": {
    "ItemCost": 0,
    "ItemRecipe": 1,
    "ItemResult": "item_satanic",
    "ItemRequirements": {
      "01": "item_lifesteal;item_claymore;item_reaver"
    }
  },
  "item_satanic": {
    "AbilityCooldown": 30.0,
    "ItemCost": 5050
  },
  "item_recipe_mjollnir": {
    "ItemCost": 550,
    "ItemRecipe": 1,
    "ItemResult": "item_mjollnir",
    "ItemRequirements": {
      "01": "item_maelstrom*;item_hyperstone"
    }
  },
  "item_mjollnir": {
    "AbilityCooldown": 35.0,
    "AbilityManaCost": 50,
    "ItemCost": 5500
  },
  "item_recipe_skadi": {
    "ItemCost": 1300,
    "ItemRecipe": 1,
    "ItemResult": "item_skadi",
    "ItemRequirements": {
      "01": "item_ultimate_orb;item_point_booster"
    }
  },
  "item_skadi": {
    "ItemCost": 5300,
    "bonus_all_stats": 22,
    "bonus_mana": 250
  },
  "item_recipe_sange": {
    "ItemCost": 650,
    "ItemRecipe": 1,
    "ItemResult": "item_sange",
    "ItemRequirements": {
      "01": "item_ogre_axe;item_belt_of_strength"
    }
  },
  "item_sange": {
    "ItemCost": 2100
  },
  "item_recipe_helm_of_the_dominator": {
    "ItemCost": 650,
    "ItemRecipe": 1,
    "ItemResult": "item_helm_of_the_dominator",
    "ItemRequirements": {
      "01": "item_helm_of_iron_will;item_diadem"
    }
  },
  "item_helm_of_the_dominator": {
    "AbilityCooldown": 45.0,
    "AbilityManaCost": 0,
    "ItemCost": 2625
  },
  "item_recipe_helm_of_the_overlord": {
    "ItemCost": 300,
    "ItemRecipe": 1,
    "ItemResult": "item_helm_of_the_overlord",
    "ItemRequirements": {
      "01": "item_helm_of_the_dominator;item_ultimate_orb"
    }
  },
  "item_helm_of_the_overlord": {
    "AbilityCooldown": 45,
    "AbilityManaCost": 0,
    "ItemCost": 5725
  },
  "item_recipe_maelstrom": {
    "ItemCost": 0,
    "ItemRecipe": 1,
    "ItemResult": "item_maelstrom",
    "ItemRequirements": {
      "01": "item_mithril_hammer;item_javelin;item_gloves"
    }
  },
  "item_maelstrom": {
    "ItemCost": 2950
  },
  "item_recipe_gungir": {
    "ItemCost": 250,
    "ItemRecipe": 1,
    "ItemResult": "item_gungir",
    "ItemRequirements": {
      "01": "item_maelstrom;item_rod_of_atos*"
    }
  },
  "item_gungir": {
    "AbilityCooldown": 18,
    "AbilityManaCost": 200,
    "ItemCost": 5450,
    "bonus_intellect": 24
  },
  "item_recipe_desolator": {
    "ItemCost": 0,
    "ItemRecipe": 1,
    "ItemResult": "item_desolator",
    "ItemRequirements": {
      "01": "item_mithril_hammer;item_mithril_hammer;item_blight_stone"
    }
  },
  "item_desolator": {
    "ItemCost": 3500
  },
  "item_recipe_yasha": {
    "ItemCost": 650,
    "ItemRecipe": 1,
    "ItemResult": "item_yasha",
    "ItemRequirements": {
      "01": "item_blade_of_alacrity;item_boots_of_elves"
    }
  },
  "item_yasha": {
    "ItemCost": 2100
  },
  "item_recipe_mask_of_madness": {
    "ItemCost": 0,
    "ItemRecipe": 1,
    "ItemResult": "item_mask_of_madness",
    "ItemRequirements": {
      "01": "item_lifesteal;item_broadsword"
    }
  },
  "item_mask_of_madness": {
    "AbilityCooldown": 16.0,
    "AbilityManaCost": 25,
    "ItemCost": 1900
  },
  "item_recipe_diffusal_blade": {
    "ItemCost": 1050,
    "ItemRecipe": 1,
    "ItemResult": "item_diffusal_blade",
    "ItemRequirements": {
      "01": "item_blade_of_alacrity;item_robe"
    }
  },
  "item_diffusal_blade": {
    "AbilityCooldown": 15.0,
    "AbilityManaCost": 25,
    "ItemCost": 2500,
    "bonus_intellect": 10
  },
  "item_recipe_disperser": {
    "ItemCost": 800,
    "ItemRecipe": 1,
    "ItemResult": "item_disperser",
    "ItemRequirements": {
      "01": "item_diffusal_blade;item_eagle"
    }
  },
  "item_disperser": {
    "AbilityCooldown": 15.0,
    "AbilityManaCost": 75,
    "ItemCost": 6100,
    "bonus_intellect": 10
  },
  "item_recipe_ethereal_blade": {
    "ItemCost": 1600,
    "ItemRecipe": 1,
    "ItemResult": "item_ethereal_blade",
    "ItemRequirements": {
      "01": "item_aether_lens;item_ghost*"
    }
  },
  "item_ethereal_blade": {
    "AbilityCooldown": 22.0,
    "AbilityManaCost": 100,
    "ItemCost": 5375,
    "bonus_intellect": 8,
    "bonus_mana": 300,
    "bonus_mana_regen": 3
  },
  "item_recipe_soul_ring": {
    "ItemCost": 350,
    "ItemRecipe": 1,
    "ItemResult": "item_soul_ring",
    "ItemRequirements": {
      "01": "item_ring_of_protection;item_gauntlets;item_gauntlets"
    }
  },
  "item_soul_ring": {
    "AbilityCooldown": 25.0,
    "ItemCost": 805,
    "mana_gain": 170
  },
  "item_recipe_arcane_boots": {
    "ItemCost": 375,
    "ItemRecipe": 1,
    "ItemResult": "item_arcane_boots",
    "ItemRequirements": {
      "01": "item_boots*;item_ring_of_basilius"
    }
  },
  "item_arcane_boots": {
    "AbilityCooldown": 55.0,
    "AbilityManaCost": 0,
    "ItemCost": 1300,
    "mana_regen": 0.75,
    "aura_mana_regen": 1,
    "replenish_amount": 175
  },
  "item_recipe_octarine_core": {
    "ItemCost": 0,
    "ItemRecipe": 1,
    "ItemResult": "item_octarine_core",
    "ItemRequirements": {
      "01": "item_tiara_of_selemene;item_soul_booster"
    }
  },
  "item_octarine_core": {
    "ItemCost": 4800,
    "bonus_mana": 550,
    "bonus_mana_regen": 6
  },
  "item_orb_of_venom": {
    "ItemCost": 250
  },
  "item_blight_stone": {
    "ItemCost": 300
  },
  "item_recipe_orb_of_corrosion": {
    "ItemCost": 0,
    "ItemRecipe": 1,
    "ItemResult": "item_orb_of_corrosion",
    "ItemRequirements": {
      "01": "item_orb_of_venom;item_ring_of_protection;item_gloves"
    }
  },
  "item_orb_of_corrosion": {
    "ItemCost": 875
  },
  "item_recipe_falcon_blade": {
    "ItemCost": 250,
    "ItemRecipe": 1,
    "ItemResult": "item_falcon_blade",
    "ItemRequirements": {
      "01": "item_fluffy_hat;item_sobi_mask;item_blades_of_attack"
    }
  },
  "item_falcon_blade": {
    "ItemCost": 1125,
    "bonus_mana_regen": 1.8
  },
  "item_recipe_mage_slayer": {
    "ItemCost": 400,
    "ItemRecipe": 1,
    "ItemResult": "item_mage_slayer",
    "ItemRequirements": {
      "01": "item_cloak;item_oblivion_staff"
    }
  },
  "item_mage_slayer": {
    "ItemCost": 2825,
    "bonus_mana_regen": 2,
    "bonus_intellect": 10
  },
  "item_recipe_ancient_janggo": {
    "ItemCost": 500,
    "ItemRecipe": 1,
    "ItemResult": "item_ancient_janggo",
    "ItemRequirements": {
      "01": "item_belt_of_strength;item_robe;item_wind_lace"
    }
  },
  "item_ancient_janggo": {
    "AbilityCooldown": 30.0,
    "ItemCost": 1650,
    "bonus_int": 7
  },
  "item_recipe_boots_of_bearing": {
    "ItemCost": 1700,
    "ItemRecipe": 1,
    "ItemResult": "item_boots_of_bearing",
    "ItemRequirements": {
      "01": "item_tranquil_boots;item_ancient_janggo"
    }
  },
  "item_boots_of_bearing": {
    "AbilityCooldown": 30.0,
    "ItemCost": 4275,
    "bonus_int": 8
  },
  "item_recipe_medallion_of_courage": {
    "ItemCost": 0,
    "ItemRecipe": 1,
    "ItemResult": "item_medallion_of_courage",
    "ItemRequirements": {
      "01": "item_chainmail;item_sobi_mask;item_blight_stone"
    }
  },
  "item_medallion_of_courage": {
    "AbilityCooldown": 16.0,
    "ItemCost": 1025
  },
  "item_recipe_solar_crest": {
    "ItemCost": 600,
    "ItemRecipe": 1,
    "ItemResult": "item_solar_crest",
    "ItemRequirements": {
      "01": "item_pavise*;item_crown;item_wind_lace"
    }
  },
  "item_solar_crest": {
    "AbilityCooldown": 16.0,
    "AbilityManaCost": 100,
    "ItemCost": 2700,
    "bonus_all_stats": 4,
    "bonus_mana": 300
  },
  "item_recipe_pavise": {
    "ItemCost": 175,
    "ItemRecipe": 1,
    "ItemResult": "item_pavise",
    "ItemRequirements": {
      "01": "item_energy_booster;item_ring_of_protection;item_fluffy_hat"
    }
  },
  "item_pavise": {
    "AbilityCooldown": 16.0,
    "AbilityManaCost": 75,
    "ItemCost": 1400,
    "bonus_mana": 250
  },
  "item_smoke_of_deceit": {
    "AbilityCooldown": 1.0,
    "ItemCost": 50
  },
  "item_tome_of_knowledge": {
    "ItemCost": 75
  },
  "item_recipe_veil_of_discord": {
    "ItemCost": 300,
    "ItemRecipe": 1,
    "ItemResult": "item_veil_of_discord",
    "ItemRequirements": {
      "01": "item_helm_of_iron_will;item_crown"
    }
  },
  "item_veil_of_discord": {
    "AbilityCooldown": 16,
    "AbilityManaCost": 50,
    "ItemCost": 1725,
    "bonus_all_stats": 4
  },
  "item_recipe_revenants_brooch": {
    "ItemCost": 800,
    "ItemRecipe": 1,
    "ItemResult": "item_revenants_brooch",
    "ItemRequirements": {
      "01": "item_relic;item_voodoo_mask"
    }
  },
  "item_revenants_brooch": {
    "ItemCost": 4900
  },
  "item_recipe_devastator": {
    "ItemCost": 400,
    "ItemRecipe": 1,
    "ItemResult": "item_devastator",
    "ItemRequirements": {
      "01": "item_witch_blade;item_mystic_staff"
    }
  },
  "item_devastator": {
    "AbilityCooldown": 7,
    "ItemCost": 5975,
    "bonus_intellect": 40,
    "bonus_mana_regen": 1.5
  },
  "item_recipe_guardian_greaves": {
    "ItemCost": 1450,
    "ItemRecipe": 1,
    "ItemResult": "item_guardian_greaves",
    "ItemRequirements": {
      "01": "item_mekansm;item_arcane_boots;item_buckler"
    }
  },
  "item_guardian_greaves": {
    "AbilityCooldown": 40,
    "AbilityManaCost": 0,
    "ItemCost": 4950,
    "mana_regen": 1.5,
    "aura_mana_regen": 1.5
  },
  "item_recipe_rod_of_atos": {
    "ItemCost": 250,
    "ItemRecipe": 1,
    "ItemResult": "item_rod_of_atos",
    "ItemRequirements": {
      "01": "item_staff_of_wizardry;item_vitality_booster"
    }
  },
  "item_rod_of_atos": {
    "AbilityCooldown": 18,
    "AbilityManaCost": 50,
    "ItemCost": 2250,
    "bonus_intellect": 15
  },
  "item_recipe_iron_talon": {
    "ItemCost": 1,
    "ItemRecipe": 1,
    "ItemResult": "item_iron_talon",
    "ItemRequirements": {
      "01": "item_quelling_blade*;item_ring_of_protection"
    }
  },
  "item_iron_talon": {
    "AbilityCooldown": 25.0,
    "AbilityManaCost": 0,
    "ItemCost": 0
  },
  "item_recipe_abyssal_blade": {
    "ItemCost": 1675,
    "ItemRecipe": 1,
    "ItemResult": "item_abyssal_blade",
    "ItemRequirements": {
      "01": "item_basher;item_vanguard"
    }
  },
  "item_abyssal_blade": {
    "AbilityCooldown": 35,
    "AbilityManaCost": 75,
    "ItemCost": 6250
  },
  "item_recipe_heavens_halberd": {
    "ItemCost": 100,
    "ItemRecipe": 1,
    "ItemResult": "item_heavens_halberd",
    "ItemRequirements": {
      "01": "item_sange;item_talisman_of_evasion"
    }
  },
  "item_heavens_halberd": {
    "AbilityCooldown": 18,
    "AbilityManaCost": 100,
    "ItemCost": 3500
  },
  "item_recipe_ring_of_aquila": {
    "ItemCost": 0,
    "ItemRecipe": 1,
    "ItemResult": "item_ring_of_aquila",
    "ItemRequirements": ""
  },
  "item_ring_of_aquila": {
    "bonus_intellect": 3,
    "aura_mana_regen": 1
  },
  "item_recipe_tranquil_boots": {
    "ItemCost": 0,
    "ItemRecipe": 1,
    "ItemResult": "item_tranquil_boots",
    "ItemRequirements": {
      "01": "item_boots;item_wind_lace;item_ring_of_regen"
    }
  },
  "item_tranquil_boots": {
    "AbilityCooldown": 13.0,
    "AbilityManaCost": 0,
    "ItemCost": 925
  },
  "item_shadow_amulet": {
    "AbilityCooldown": 7.0,
    "AbilityManaCost": 0,
    "ItemCost": 1000
  },
  "item_recipe_glimmer_cape": {
    "ItemCost": 350,
    "ItemRecipe": 1,
    "ItemResult": "item_glimmer_cape",
    "ItemRequirements": {
      "01": "item_shadow_amulet*;item_cloak"
    }
  },
  "item_glimmer_cape": {
    "AbilityCooldown": 14.0,
    "AbilityManaCost": 90,
    "ItemCost": 2150
  },
  "item_river_painter": {
    "AbilityCooldown": 0.0,
    "ItemCost": 0
  },
  "item_river_painter2": {
    "AbilityCooldown": 0.0,
    "ItemCost": 0
  },
  "item_river_painter3": {
    "AbilityCooldown": 0.0,
    "ItemCost": 0
  },
  "item_river_painter4": {
    "AbilityCooldown": 0.0,
    "ItemCost": 0
  },
  "item_river_painter5": {
    "AbilityCooldown": 0.0,
    "ItemCost": 0
  },
  "item_river_painter6": {
    "AbilityCooldown": 0.0,
    "ItemCost": 0
  },
  "item_river_painter7": {
    "AbilityCooldown": 0.0,
    "ItemCost": 0
  },
  "item_mutation_tombstone": {
    "ItemCost": 0
  },
  "item_super_blink": {
    "AbilityCooldown": 15.0,
    "AbilityManaCost": 0
  },
  "item_pocket_tower": {
    "AbilityCooldown": 15.0,
    "AbilityManaCost": 0
  },
  "item_pocket_roshan": {
    "AbilityCooldown": 60.0,
    "AbilityManaCost": 0,
    "ItemCost": 1000
  },
  "item_keen_optic": {
    "ItemCost": 0,
    "bonus_mana_regen": 1.25
  },
  "item_grove_bow": {
    "ItemCost": 0
  },
  "item_quickening_charm": {
    "ItemCost": 0
  },
  "item_philosophers_stone": {
    "ItemCost": 0,
    "bonus_mana": 200
  },
  "item_force_boots": {
    "AbilityCooldown": 8.0,
    "AbilityManaCost": 75,
    "ItemCost": 0
  },
  "item_desolator_2": {
    "ItemCost": 0
  },
  "item_phoenix_ash": {
    "ItemCost": 0
  },
  "item_seer_stone": {
    "AbilityCooldown": 60,
    "ItemCost": 0,
    "mana_regen": 10
  },
  "item_greater_mango": {
    "ItemCost": 0
  },
  "item_elixer": {
    "ItemCost": 0
  },
  "item_vampire_fangs": {
    "ItemCost": 0
  },
  "item_force_field": {
    "ItemCost": 0,
    "AbilityCooldown": 20
  },
  "item_black_powder_bag": {
    "ItemCost": 0,
    "AbilityCooldown": 20
  },
  "item_mechanical_arm": {
    "ItemCost": 0
  },
  "item_craggy_coat": {
    "AbilityCooldown": 12,
    "ItemCost": 0
  },
  "item_greater_faerie_fire": {
    "ItemCost": 0,
    "AbilityCooldown": 10.0
  },
  "item_timeless_relic": {
    "ItemCost": 0
  },
  "item_mirror_shield": {
    "ItemCost": 0
  },
  "item_recipe_ironwood_tree": {
    "ItemCost": 1,
    "ItemRecipe": 1,
    "ItemResult": "item_ironwood_tree"
  },
  "item_ironwood_tree": {
    "AbilityCooldown": 15.0,
    "ItemCost": 0,
    "bonus_all_stats": 6
  },
  "item_royal_jelly": {
    "ItemCost": 0,
    "bonus_mana": 50,
    "mana_regen": 1.25
  },
  "item_pupils_gift": {
    "ItemCost": 0
  },
  "item_tome_of_aghanim": {
    "ItemCost": 0
  },
  "item_repair_kit": {
    "ItemCost": 0,
    "AbilityCooldown": 60.0
  },
  "item_mind_breaker": {
    "ItemCost": 0,
    "AbilityCooldown": 12.0
  },
  "item_third_eye": {
    "ItemCost": 0,
    "bonus_all_stats": 7
  },
  "item_spell_prism": {
    "ItemCost": 0,
    "bonus_all_stats": 5,
    "mana_regen": 2
  },
  "item_princes_knife": {
    "ItemCost": 0,
    "AbilityCooldown": 10.0
  },
  "item_witless_shako": {
    "ItemCost": 0,
    "max_mana": 400
  },
  "item_imp_claw": {
    "AbilityCooldown": 7.0,
    "ItemCost": 0
  },
  "item_flicker": {
    "AbilityCooldown": 5.0,
    "ItemCost": 0
  },
  "item_spy_gadget": {
    "ItemCost": 0
  },
  "item_spider_legs": {
    "AbilityCooldown": 12.0,
    "ItemCost": 0
  },
  "item_helm_of_the_undying": {
    "ItemCost": 0,
    "AbilityCooldown": 0.0
  },
  "item_vambrace": {
    "ItemCost": 0
  },
  "item_horizon": {
    "AbilityCooldown": 10.0,
    "ItemCost": 0
  },
  "item_fusion_rune": {
    "ItemCost": 0,
    "AbilityCooldown": 120.0
  },
  "item_ocean_heart": {
    "ItemCost": 0
  },
  "item_spark_of_courage": {
    "ItemCost": 0
  },
  "item_broom_handle": {
    "ItemCost": 0
  },
  "item_trusty_shovel": {
    "AbilityCooldown": 40.0,
    "ItemCost": 0
  },
  "item_nether_shawl": {
    "ItemCost": 0
  },
  "item_dragon_scale": {
    "ItemCost": 0
  },
  "item_essence_ring": {
    "AbilityCooldown": 25.0,
    "AbilityManaCost": 200,
    "ItemCost": 0,
    "bonus_int": 10,
    "mp_regen": 2.5
  },
  "item_clumsy_net": {
    "AbilityCooldown": 25.0,
    "ItemCost": 0,
    "mana_regen": 2
  },
  "item_enchanted_quiver": {
    "AbilityCooldown": 4.0,
    "ItemCost": 0
  },
  "item_ninja_gear": {
    "AbilityCooldown": 60.0,
    "ItemCost": 0
  },
  "item_illusionsts_cape": {
    "AbilityCooldown": 30.0,
    "ItemCost": 0
  },
  "item_havoc_hammer": {
    "AbilityCooldown": 10.0,
    "ItemCost": 0
  },
  "item_panic_button": {
    "AbilityCooldown": 75.0,
    "ItemCost": 0
  },
  "item_apex": {
    "ItemCost": 0
  },
  "item_ballista": {
    "ItemCost": 0
  },
  "item_woodland_striders": {
    "AbilityCooldown": 20.0,
    "ItemCost": 0
  },
  "item_recipe_trident": {
    "ItemCost": 1,
    "ItemRecipe": 1,
    "ItemResult": "item_trident",
    "ItemRequirements": {
      "01": "item_kaya;item_sange;item_yasha;",
      "02": "item_kaya_and_sange;item_yasha;",
      "03": "item_sange_and_yasha;item_kaya;",
      "04": "item_yasha_and_kaya;item_sange;"
    }
  },
  "item_demonicon": {
    "AbilityCooldown": 80.0,
    "ItemCost": 0,
    "bonus_intellect": 25
  },
  "item_recipe_fallen_sky": {
    "ItemCost": 0,
    "ItemRecipe": 1,
    "ItemResult": "item_fallen_sky",
    "ItemRequirements": ""
  },
  "item_fallen_sky": {
    "AbilityCooldown": 15.0,
    "ItemCost": 0,
    "bonus_intellect": 15,
    "bonus_mana_regen": 10.0
  },
  "item_pirate_hat": {
    "AbilityCooldown": 40.0,
    "ItemCost": 0
  },
  "item_dimensional_doorway": {
    "AbilityCooldown": 90.0,
    "ItemCost": 0
  },
  "item_ex_machina": {
    "AbilityCooldown": 25.0,
    "AbilityManaCost": 350,
    "ItemCost": 0
  },
  "item_faded_broach": {
    "ItemCost": 0,
    "bonus_mana": 150
  },
  "item_paladin_sword": {
    "ItemCost": 0
  },
  "item_minotaur_horn": {
    "AbilityCooldown": 40.0,
    "ItemCost": 0
  },
  "item_orb_of_destruction": {
    "ItemCost": 0
  },
  "item_the_leveller": {
    "ItemCost": 0
  },
  "item_arcane_ring": {
    "AbilityCooldown": 60.0,
    "ItemCost": 0,
    "bonus_intelligence": 6,
    "mana_restore": 75
  },
  "item_titan_sliver": {
    "ItemCost": 0
  },
  "item_chipped_vest": {
    "ItemCost": 0
  },
  "item_wizard_glass": {
    "AbilityCooldown": 15.0,
    "ItemCost": 0
  },
  "item_gloves_of_travel": {
    "ItemCost": 0
  },
  "item_elven_tunic": {
    "ItemCost": 0
  },
  "item_cloak_of_flames": {
    "ItemCost": 0
  },
  "item_venom_gland": {
    "ItemCost": 0
  },
  "item_trickster_cloak": {
    "ItemCost": 0,
    "AbilityCooldown": 25.0
  },
  "item_gladiator_helm": {
    "ItemCost": 0
  },
  "item_possessed_mask": {
    "ItemCost": 0
  },
  "item_ancient_perseverance": {
    "ItemCost": 0
  },
  "item_star_mace": {
    "ItemCost": 0,
    "bonus_mana_regen": 1
  },
  "item_penta_edged_sword": {
    "ItemCost": 0
  },
  "item_oakheart": {
    "AbilityManaCost": 75,
    "ItemCost": 0,
    "AbilityCooldown": 18.0
  },
  "item_warhammer": {
    "ItemCost": 0,
    "AbilityCooldown": 20.0
  },
  "item_bullwhip": {
    "ItemCost": 0,
    "AbilityCooldown": 11.0,
    "bonus_mana_regen": 2
  },
  "item_psychic_headband": {
    "ItemCost": 0,
    "AbilityCooldown": 20.0
  },
  "item_ceremonial_robe": {
    "ItemCost": 0,
    "bonus_mana": 300
  },
  "item_quicksilver_amulet": {
    "ItemCost": 0
  },
  "item_book_of_shadows": {
    "ItemCost": 0,
    "AbilityCooldown": 8.0,
    "bonus_all_stats": 13
  },
  "item_giants_ring": {
    "ItemCost": 0
  },
  "item_vengeances_shadow": {
    "ItemCost": 0
  },
  "item_stormcrafter": {
    "ItemCost": 0,
    "AbilityCooldown": 3.0,
    "bonus_mana_regen": 4
  },
  "item_overflowing_elixir": {
    "ItemCost": 0,
    "AbilityCooldown": 45.0
  },
  "item_mysterious_hat": {
    "ItemCost": 0,
    "AbilityCooldown": 8.0
  },
  "item_assassins_dagger": {
    "ItemCost": 0,
    "AbilityCooldown": 7.0
  },
  "item_ascetic_cap": {
    "ItemCost": 0,
    "AbilityCooldown": 25.0,
    "AbilityManaCost": 0
  },
  "item_sample_picker": {
    "ItemCost": 0,
    "AbilityCooldown": 15.0,
    "AbilityManaCost": 0
  },
  "item_icarus_wings": {
    "ItemCost": 0,
    "AbilityCooldown": 45.0,
    "AbilityManaCost": 0
  },
  "item_misericorde": {
    "ItemCost": 0
  },
  "item_light_robes": {
    "ItemCost": 0
  },
  "item_heavy_blade": {
    "AbilityCooldown": 20,
    "AbilityManaCost": "75 75 75 75",
    "ItemCost": 0
  },
  "item_unstable_wand": {
    "AbilityCooldown": 25.0,
    "AbilityManaCost": 50,
    "ItemCost": 0
  },
  "item_fortitude_ring": {
    "AbilityCooldown": 30.0,
    "AbilityManaCost": 100,
    "ItemCost": 0
  },
  "item_pogo_stick": {
    "ItemCost": 0,
    "AbilityCooldown": 15.0,
    "bonus_mana": 150
  },
  "item_paintball": {
    "ItemCost": 0,
    "AbilityCooldown": 20.0,
    "AbilityManaCost": 25
  },
  "item_seeds_of_serenity": {
    "ItemCost": 0,
    "AbilityCooldown": 35.0
  },
  "item_lance_of_pursuit": {
    "ItemCost": 0,
    "bonus_mana": 200
  },
  "item_occult_bracelet": {
    "ItemCost": 0,
    "bonus_all_stats": 3,
    "mana_regen": 0.4
  },
  "item_tome_of_omniscience": {
    "ItemCost": 0,
    "bonus_mana": 200
  },
  "item_ogre_seal_totem": {
    "ItemCost": 0,
    "AbilityCooldown": 40.0,
    "AbilityManaCost": 25
  },
  "item_wand_of_the_brine": {
    "AbilityCooldown": 35.0,
    "AbilityManaCost": 90,
    "ItemCost": 0
  },
  "item_slime_vial": {
    "AbilityCooldown": 27,
    "ItemCost": 0
  },
  "item_recipe_harpoon": {
    "ItemCost": 1000,
    "ItemRecipe": 1,
    "ItemResult": "item_harpoon",
    "ItemRequirements": {
      "01": "item_echo_sabre;item_diadem"
    }
  },
  "item_harpoon": {
    "AbilityCooldown": 19.0,
    "AbilityManaCost": 50,
    "ItemCost": 4700,
    "bonus_intellect": 10,
    "bonus_mana_regen": 2.0
  },
  "item_defiant_shell": {
    "ItemCost": 0
  },
  "item_arcane_scout": {
    "ItemCost": 0,
    "AbilityCooldown": 40.0
  },
  "item_barricade": {
    "ItemCost": 0,
    "AbilityCooldown": 45.0
  },
  "item_eye_of_the_vizier": {
    "ItemCost": 0,
    "bonus_mana_regen": 1.25
  },
  "item_manacles_of_power": {
    "ItemCost": 0,
    "AbilityCooldown": 20.0
  },
  "item_bottomless_chalice": {
    "AbilityCooldown": 0.5,
    "ItemCost": 0,
    "bonus_intellect": 40
  },
  "item_wand_of_sanctitude": {
    "ItemCost": 0,
    "AbilityCooldown": 40.0
  },
  "item_specialists_array": {
    "AbilityCooldown": 8.0,
    "ItemCost": 0
  },
  "item_dagger_of_ristul": {
    "AbilityCooldown": 30.0,
    "ItemCost": 0
  },
  "item_ofrenda": {
    "AbilityCooldown": 3,
    "ItemCost": 0,
    "AbilityDamage": 0,
    "AbilityManaCost": 0
  },
  "item_ofrenda_shovel": {
    "ItemCost": 0,
    "AbilityCooldown": 8,
    "AbilityDamage": 0,
    "AbilityManaCost": 0
  },
  "item_ofrenda_pledge": {
    "ItemCost": 0,
    "AbilityCooldown": 0.5,
    "AbilityDamage": 0,
    "AbilityManaCost": 0
  },
  "item_muertas_gun": {
    "AbilityCooldown": 10,
    "AbilityManaCost": 160,
    "ItemCost": 0
  },
  "item_vindicators_axe": {
    "ItemCost": 0
  },
  "item_duelist_gloves": {
    "ItemCost": 0
  },
  "item_ancient_guardian": {
    "ItemCost": 0
  },
  "item_safety_bubble": {
    "ItemCost": 0
  },
  "item_whisper_of_the_dread": {
    "ItemCost": 0,
    "bonus_mana": 150
  },
  "item_nemesis_curse": {
    "ItemCost": 0
  },
  "item_avianas_feather": {
    "ItemCost": 0
  },
  "item_unwavering_condition": {
    "ItemCost": 0
  },
  "item_horizons_equilibrium": {
    "ItemCost": 0
  },
  "item_blighted_spirit": {
    "ItemCost": 0
  },
  "item_dandelion_amulet": {
    "AbilityCooldown": 12,
    "ItemCost": 0
  },
  "item_turtle_shell": {
    "ItemCost": 0,
    "AbilityCooldown": 30
  },
  "item_martyrs_plate": {
    "ItemCost": 0,
    "AbilityCooldown": 40
  },
  "item_gossamer_cape": {
    "ItemCost": 0,
    "AbilityCooldown": 4
  },
  "item_light_collector": {
    "ItemCost": 0,
    "AbilityCooldown": 30,
    "mana_regen": 6
  },
  "item_rattlecage": {
    "ItemCost": 0
  },
  "item_doubloon": {
    "ItemCost": 0,
    "AbilityCooldown": 5,
    "bonus_mana_regen": 2.5
  },
  "item_roshans_banner": {
    "AbilityCooldown": 1.0,
    "ItemCost": 0
  },
  "item_black_grimoire": {
    "AbilityCooldown": 420,
    "ItemCost": 0
  },
  "item_grisgris": {
    "ItemCost": 0
  }
}